{
    "project_name": "Package name",
    "author_name": "Your name",
    "author_email": "Your email",
    "short_description": "Your brief project description...",

    "package_name": "{{cookiecutter.project_name|lower|replace(' ', '_')|replace('-', '_')}}",
    "package_version": "0.1.0",
    "github_username": "Your GitHub username",
    "github_base_url": "https://www.github.com/{{cookiecutter.gitlab_username}}",
    "project_url": "{{cookiecutter.github_base_url}}/{{cookiecutter.package_name}}"
}
